<annotations><filename>Walt Disney Uncle Scrooge and Donald Duck - Treasure Under Glass v3-100.JPEG</filename><folder>images</folder><size><width>463</width><height>600</height><depth>3</depth></size><object><name>pratbubbla</name><pose>Unspecified</pose><truncated>0</truncated><difficult>0</difficult><bndbox><xmin>242.00000000000006</xmin><ymin>25.000000000000004</ymin><xmax>337.00000000000006</xmax><ymax>67.00000000000001</ymax></bndbox></object><object><name>pratbubbla</name><pose>Unspecified</pose><truncated>0</truncated><difficult>0</difficult><bndbox><xmin>41.0</xmin><ymin>166.0</ymin><xmax>135.0</xmax><ymax>229.0</ymax></bndbox></object><object><name>pratbubbla</name><pose>Unspecified</pose><truncated>0</truncated><difficult>0</difficult><bndbox><xmin>249.00000000000006</xmin><ymin>165.0</ymin><xmax>359.00000000000006</xmax><ymax>208.0</ymax></bndbox></object><object><name>pratbubbla</name><pose>Unspecified</pose><truncated>0</truncated><difficult>0</difficult><bndbox><xmin>364.0</xmin><ymin>163.0</ymin><xmax>423.0</xmax><ymax>203.0</ymax></bndbox></object><object><name>pratbubbla</name><pose>Unspecified</pose><truncated>0</truncated><difficult>0</difficult><bndbox><xmin>128.00000000000003</xmin><ymin>303.0</ymin><xmax>220.00000000000003</xmax><ymax>368.0</ymax></bndbox></object><object><name>pratbubbla</name><pose>Unspecified</pose><truncated>0</truncated><difficult>0</difficult><bndbox><xmin>225.0</xmin><ymin>303.0</ymin><xmax>332.0</xmax><ymax>350.0</ymax></bndbox></object><object><name>pratbubbla</name><pose>Unspecified</pose><truncated>0</truncated><difficult>0</difficult><bndbox><xmin>344.0</xmin><ymin>300.00000000000006</ymin><xmax>410.0</xmax><ymax>332.00000000000006</ymax></bndbox></object><object><name>pratbubbla</name><pose>Unspecified</pose><truncated>0</truncated><difficult>0</difficult><bndbox><xmin>234.00000000000006</xmin><ymin>441.0</ymin><xmax>356.00000000000006</xmax><ymax>477.0</ymax></bndbox></object><object><name>pratbubbla</name><pose>Unspecified</pose><truncated>0</truncated><difficult>0</difficult><bndbox><xmin>363.00000000000006</xmin><ymin>441.0</ymin><xmax>419.00000000000006</xmax><ymax>476.0</ymax></bndbox></object><object><name>pratbubbla</name><pose>Unspecified</pose><truncated>0</truncated><difficult>0</difficult><bndbox><xmin>44.0</xmin><ymin>517.0</ymin><xmax>145.0</xmax><ymax>568.0</ymax></bndbox></object></annotations>